{
"label": "x",
"gestures": [
{
"l_hand_position": null,
"l_wrist": null,
"l_thumb_cmc": null,
"l_thumb_mcp": null,
"l_thumb_ip": null,
"l_thumb_tip": null,
"l_index_mcp": null,
"l_index_pip": null,
"l_index_dip": null,
"l_index_tip": null,
"l_middle_mcp": null,
"l_middle_pip": null,
"l_middle_dip": null,
"l_middle_tip": null,
"l_ring_mcp": null,
"l_ring_pip": null,
"l_ring_dip": null,
"l_ring_tip": null,
"l_pinky_mcp": null,
"l_pinky_pip": null,
"l_pinky_dip": null,
"l_pinky_tip": null,
"r_hand_position": [
-0.23211431503295898,
0.03345906734466553,
0.5066857016645372
],
"r_wrist": [
-0.10277095582324829,
0.9933395468151532,
-0.05210254669631871
],
"r_thumb_cmc": [
0.1528844251360974,
0.7843320678305298,
0.0269827429519343
],
"r_thumb_mcp": [
0.2330783314972101,
0.37860103880165324,
0.06674365866825452
],
"r_thumb_ip": [
0.07022035564616033,
0.07618813599199249,
0.12054213828522785
],
"r_thumb_tip": [
-0.12952192139587948,
-0.04135688501337623,
0.16629476289146322
],
"r_index_mcp": [
0.200935089925609,
-0.0005657500358984719,
-0.04249899943025093
],
"r_index_pip": [
0.2385021928840627,
-0.3074442693029713,
0.07960899970037133
],
"r_index_dip": [
0.22975350493156046,
-0.4788539889232549,
0.17066681344341036
],
"r_index_tip": [
0.22298680006869598,
-0.503157319180478,
0.2214266219803586
],
"r_middle_mcp": [
-0.0,
0.0,
-0.0
],
"r_middle_pip": [
-0.07243179728894575,
-0.4177169869938536,
0.14944777599144907
],
"r_middle_dip": [
-0.04474813379177914,
-0.5436530378830532,
0.24533202860549738
],
"r_middle_tip": [
-0.02086911606147984,
-0.5049778916482154,
0.2785288228532475
],
"r_ring_mcp": [
-0.16858050494979293,
0.1251459517011344,
0.06042969463294267
],
"r_ring_pip": [
-0.19459943270914334,
-0.07891934306184718,
0.20905330755350784
],
"r_ring_dip": [
-0.08540735332574691,
0.15202883271727557,
0.22559310623488182
],
"r_ring_tip": [
-0.02182875446391518,
0.3389200373100518,
0.19168955990256953
],
"r_pinky_mcp": [
-0.3163285886269697,
0.3130423148141769,
0.12964722147149998
],
"r_pinky_pip": [
-0.26539111228318146,
0.24942702116348148,
0.22758124383024672
],
"r_pinky_dip": [
-0.1649231028293787,
0.41723507758314377,
0.21675305870915645
],
"r_pinky_tip": [
-0.10381931200635407,
0.5436193622856782,
0.18006432274378373
],
"l_hand_velocity": null,
"r_hand_velocity": null,
"m_nose_point": null,
"m_top_nose": null,
"m_eyebrows": null,
"m_forehead": null,
"m_top_chin": null,
"m_bot_up_lip": null,
"m_top_low_lip": null,
"m_bot_nose": null,
"m_chin": null,
"m_nose": null,
"l_eye_exterior": null,
"l_temple": null,
"l_mid_chin": null,
"l_up_lip": null,
"l_ext_nostril": null,
"l_mid_cheek": null,
"l_mid_eyebrow": null,
"l_ext_eyebrow": null,
"l_ext_lips": null,
"l_jaw_angle": null,
"l_mid_ext_face": null,
"l_int_eyebrow": null,
"l_mid_jaw": null,
"l_mid_bot_eyelid": null,
"l_ext_mouth": null,
"l_top_eyelid": null,
"l_eye_int": null,
"l_pupil": null,
"r_eye_exterior": null,
"r_temple": null,
"r_mid_chin": null,
"r_up_lip": null,
"r_ext_nostril": null,
"r_mid_cheek": null,
"r_mid_eyebrow": null,
"r_ext_eyebrow": null,
"r_ext_lips": null,
"r_jaw_angle": null,
"r_mid_ext_face": null,
"r_int_eyebrow": null,
"r_mid_jaw": null,
"r_mid_bot_eyelid": null,
"r_ext_mouth": null,
"r_top_eyelid": null,
"r_eye_int": null,
"r_pupil": null,
"l_shoulder": null,
"l_elbow": null,
"l_hip": null,
"l_knee": null,
"l_ankle": null,
"l_body_wrist": null,
"r_shoulder": null,
"r_elbow": null,
"r_hip": null,
"r_knee": null,
"r_ankle": null,
"r_body_wrist": null,
"m_face_position": null,
"m_body_position": null,
"m_face_scale": null,
"m_body_scale": null,
"l_hand_scale": null,
"r_hand_scale": [
-0.12832249709207993,
0.12832249709207993,
-0.12832249709207993
]
}
],
"framerate": 30,
"mirrorable": true,
"invalid": false
}