{
"label": "j",
"gestures": [
{
"l_hand_position": null,
"l_wrist": null,
"l_thumb_cmc": null,
"l_thumb_mcp": null,
"l_thumb_ip": null,
"l_thumb_tip": null,
"l_index_mcp": null,
"l_index_pip": null,
"l_index_dip": null,
"l_index_tip": null,
"l_middle_mcp": null,
"l_middle_pip": null,
"l_middle_dip": null,
"l_middle_tip": null,
"l_ring_mcp": null,
"l_ring_pip": null,
"l_ring_dip": null,
"l_ring_tip": null,
"l_pinky_mcp": null,
"l_pinky_pip": null,
"l_pinky_dip": null,
"l_pinky_tip": null,
"r_hand_position": [
-0.1943402886390686,
0.02686673402786255,
0.49977395030146
],
"r_wrist": [
-0.00015600124542117515,
0.999996991645782,
0.002447930349696785
],
"r_thumb_cmc": [
0.3593372654292572,
0.679734170395056,
0.08471792287919501
],
"r_thumb_mcp": [
0.6195131772297636,
0.22796745632024362,
0.125982568943822
],
"r_thumb_ip": [
0.7924876160060608,
-0.11390733912052509,
0.18604197068476705
],
"r_thumb_tip": [
0.9421611414889952,
-0.3474663442126004,
0.22629550950376134
],
"r_index_mcp": [
0.22509754911109042,
-0.0643053894090468,
-0.02432272481882839
],
"r_index_pip": [
0.23193775247953707,
-0.38751031679242676,
0.13183104435358006
],
"r_index_dip": [
0.2998002281374849,
-0.12700950983616716,
0.22343190761354112
],
"r_index_tip": [
0.3481728622497145,
0.12763222555136078,
0.24719101413096184
],
"r_middle_mcp": [
-0.0,
0.0,
-0.0
],
"r_middle_pip": [
0.024983406064227536,
-0.3259207672468486,
0.2067234570744476
],
"r_middle_dip": [
0.13902482889982537,
-0.019310633503457533,
0.30924145630231364
],
"r_middle_tip": [
0.21601724521438517,
0.2621207703023068,
0.3217922238555502
],
"r_ring_mcp": [
-0.21479888838031072,
0.08068036311230586,
0.04941247302044516
],
"r_ring_pip": [
-0.19117501383093136,
-0.15255696999024398,
0.24470508674347355
],
"r_ring_dip": [
-0.04699182970027853,
0.14768676582017384,
0.2779573444617914
],
"r_ring_tip": [
0.059083860120156234,
0.39858962838355794,
0.22952463858899283
],
"r_pinky_mcp": [
-0.4262295680526642,
0.18153645754358666,
0.1032375511007946
],
"r_pinky_pip": [
-0.47441848168991435,
-0.21732649533608106,
0.19259069910228407
],
"r_pinky_dip": [
-0.48542108192482597,
-0.4898671174193295,
0.2048835126333592
],
"r_pinky_tip": [
-0.47914106484675534,
-0.7416499043628785,
0.1835606765987311
],
"l_hand_velocity": null,
"r_hand_velocity": null,
"m_nose_point": null,
"m_top_nose": null,
"m_eyebrows": null,
"m_forehead": null,
"m_top_chin": null,
"m_bot_up_lip": null,
"m_top_low_lip": null,
"m_bot_nose": null,
"m_chin": null,
"m_nose": null,
"l_eye_exterior": null,
"l_temple": null,
"l_mid_chin": null,
"l_up_lip": null,
"l_ext_nostril": null,
"l_mid_cheek": null,
"l_mid_eyebrow": null,
"l_ext_eyebrow": null,
"l_ext_lips": null,
"l_jaw_angle": null,
"l_mid_ext_face": null,
"l_int_eyebrow": null,
"l_mid_jaw": null,
"l_mid_bot_eyelid": null,
"l_ext_mouth": null,
"l_top_eyelid": null,
"l_eye_int": null,
"l_pupil": null,
"r_eye_exterior": null,
"r_temple": null,
"r_mid_chin": null,
"r_up_lip": null,
"r_ext_nostril": null,
"r_mid_cheek": null,
"r_mid_eyebrow": null,
"r_ext_eyebrow": null,
"r_ext_lips": null,
"r_jaw_angle": null,
"r_mid_ext_face": null,
"r_int_eyebrow": null,
"r_mid_jaw": null,
"r_mid_bot_eyelid": null,
"r_ext_mouth": null,
"r_top_eyelid": null,
"r_eye_int": null,
"r_pupil": null,
"l_shoulder": null,
"l_elbow": null,
"l_hip": null,
"l_knee": null,
"l_ankle": null,
"l_body_wrist": null,
"r_shoulder": null,
"r_elbow": null,
"r_hip": null,
"r_knee": null,
"r_ankle": null,
"r_body_wrist": null,
"m_face_position": null,
"m_body_position": null,
"m_face_scale": null,
"m_body_scale": null,
"l_hand_scale": null,
"r_hand_scale": [
-0.09246287743858368,
0.09246287743858368,
-0.09246287743858368
]
}
],
"framerate": 30,
"mirrorable": true,
"invalid": false
}